{
  "fechaprediccion": "2017-08-02",
  "horaprediccion": "15:55",
  "nomett": "CERRO EL PLOMO / ESQ.Ÿ URANO",
  "paradero": "PC1142",
  "respuestaParadero": "",
  "servicios": {
    "item": [
      {
        "codigorespuesta": "01",
        "distanciabus1": "906",
        "distanciabus2": null,
        "horaprediccionbus1": "Menos de 5 min.",
        "horaprediccionbus2": null,
        "ppubus1": "FZJL-73",
        "ppubus2": null,
        "respuestaServicio": "",
        "servicio": "C14",
        "color": "#ED1C24",
        "destino": "Los Trapenses",
        "sentido": "1",
        "itinerario": false,
        "codigo": "U6"
      }
    ]
  },
  "urlLinkPublicidad": null,
  "urlPublicidad": "http://mkt.smsbus.cl/img/Cat11.jpg",
  "x": "-",
  "y": "-",
  "valid": true,
  "lat": null,
  "lng": null
}