{
  "fechaprediccion": "2017-08-02",
  "horaprediccion": "15:57",
  "nomett": "AV. APOSTOL SANTIAGO ESQ. / PUERTO MONTT",
  "paradero": "PB1515",
  "respuestaParadero": "",
  "servicios": {
    "item": [
      {
        "codigorespuesta": "00",
        "distanciabus1": "4968",
        "distanciabus2": "6858",
        "horaprediccionbus1": "Entre 11 Y 19 min. ",
        "horaprediccionbus2": "Entre 18 Y 28 min. ",
        "ppubus1": "CJRY-52",
        "ppubus2": "SW-6941",
        "respuestaServicio": "",
        "servicio": "B24",
        "color": "#ED1C24",
        "destino": "Huamachuco",
        "sentido": "2",
        "itinerario": false,
        "codigo": "U6"
      }
    ]
  },
  "urlLinkPublicidad": null,
  "urlPublicidad": "http://mkt.smsbus.cl/img/Cat11.jpg",
  "x": "-",
  "y": "-",
  "valid": true,
  "googleMaps": {
    "address_components": [
      {
        "long_name": "Chile",
        "short_name": "CL",
        "types": [
          "country",
          "political"
        ]
      },
      {
        "long_name": "Renca",
        "short_name": "Renca",
        "types": [
          "locality",
          "political"
        ]
      },
      {
        "long_name": "Renca",
        "short_name": "Renca",
        "types": [
          "administrative_area_level_3",
          "political"
        ]
      },
      {
        "long_name": "Santiago",
        "short_name": "Santiago",
        "types": [
          "administrative_area_level_2",
          "political"
        ]
      },
      {
        "long_name": "Región Metropolitana",
        "short_name": "Región Metropolitana",
        "types": [
          "administrative_area_level_1",
          "political"
        ]
      }
    ],
    "formatted_address": "Renca, Región Metropolitana, Chile",
    "geometry": {
      "location": {
        "lat": -33.3968115,
        "lng": -70.699544
      },
      "location_type": "GEOMETRIC_CENTER",
      "viewport": {
        "northeast": {
          "lat": -33.3954625197085,
          "lng": -70.6981950197085
        },
        "southwest": {
          "lat": -33.39816048029149,
          "lng": -70.70089298029151
        }
      }
    },
    "place_id": "ChIJL5iDg7vGYpYREAU7cC6PNF4",
    "types": [
      "bus_station",
      "establishment",
      "point_of_interest",
      "transit_station"
    ]
  },
  "lat": -33.3968115,
  "lng": -70.699544
}