{
  "fechaprediccion": "2017-08-02",
  "horaprediccion": "15:55",
  "nomett": "PEDRO DONOSO ESQ. / MARIA EUGENIA",
  "paradero": "PB5",
  "respuestaParadero": "",
  "servicios": {
    "item": [
      {
        "codigorespuesta": "01",
        "distanciabus1": "409",
        "distanciabus2": null,
        "horaprediccionbus1": "Menos de 5 min.",
        "horaprediccionbus2": null,
        "ppubus1": "CJRF-11",
        "ppubus2": null,
        "respuestaServicio": "",
        "servicio": "101",
        "color": "#00A1E4",
        "destino": "Cerrillos",
        "sentido": "1",
        "itinerario": false,
        "codigo": "U1"
      },
      {
        "codigorespuesta": "00",
        "distanciabus1": "1903",
        "distanciabus2": "3263",
        "horaprediccionbus1": "Entre 05 Y 09 min. ",
        "horaprediccionbus2": "Entre 10 Y 16 min. ",
        "ppubus1": "ZN-5404",
        "ppubus2": "ZN-6530",
        "respuestaServicio": "",
        "servicio": "107",
        "color": "#00A1E4",
        "destino": "Av. Departamental",
        "sentido": "1",
        "itinerario": false,
        "codigo": "U1"
      },
      {
        "codigorespuesta": "11",
        "distanciabus1": null,
        "distanciabus2": null,
        "horaprediccionbus1": null,
        "horaprediccionbus2": null,
        "ppubus1": null,
        "ppubus2": null,
        "respuestaServicio": "Fuera de horario de operacion para este paradero",
        "servicio": "107C",
        "color": "#00A1E4",
        "destino": "Plaza Renca",
        "sentido": "1",
        "itinerario": false,
        "codigo": "U1"
      }
    ]
  },
  "urlLinkPublicidad": null,
  "urlPublicidad": "http://mkt.smsbus.cl/img/Cat11.jpg",
  "x": "-",
  "y": "-",
  "valid": true,
  "googleMaps": {
    "address_components": [
      {
        "long_name": "Chile",
        "short_name": "CL",
        "types": [
          "country",
          "political"
        ]
      },
      {
        "long_name": "Recoleta",
        "short_name": "Recoleta",
        "types": [
          "locality",
          "political"
        ]
      },
      {
        "long_name": "Recoleta",
        "short_name": "Recoleta",
        "types": [
          "administrative_area_level_3",
          "political"
        ]
      },
      {
        "long_name": "Santiago",
        "short_name": "Santiago",
        "types": [
          "administrative_area_level_2",
          "political"
        ]
      },
      {
        "long_name": "Región Metropolitana",
        "short_name": "Región Metropolitana",
        "types": [
          "administrative_area_level_1",
          "political"
        ]
      }
    ],
    "formatted_address": "Recoleta, Región Metropolitana, Chile",
    "geometry": {
      "location": {
        "lat": -33.3986478,
        "lng": -70.6352858
      },
      "location_type": "GEOMETRIC_CENTER",
      "viewport": {
        "northeast": {
          "lat": -33.3972988197085,
          "lng": -70.63393681970851
        },
        "southwest": {
          "lat": -33.3999967802915,
          "lng": -70.63663478029152
        }
      }
    },
    "place_id": "ChIJT9NyQQjGYpYRLT51YTOXTmg",
    "types": [
      "bus_station",
      "establishment",
      "point_of_interest",
      "transit_station"
    ]
  },
  "lat": -33.3986478,
  "lng": -70.6352858
}