{
  "fechaprediccion": "2017-08-01",
  "horaprediccion": "13:39",
  "nomett": "LO OVALLE ESQ. / DEL TRIGAL",
  "paradero": "PB942",
  "respuestaParadero": "",
  "servicios": {
    "item": [
      {
        "codigorespuesta": "00",
        "distanciabus1": "5026",
        "distanciabus2": "5546",
        "horaprediccionbus1": "Entre 17 Y 27 min. ",
        "horaprediccionbus2": "Entre 18 Y 28 min. ",
        "ppubus1": "CCPX-45",
        "ppubus2": "CJRF-64",
        "respuestaServicio": "",
        "servicio": "B06",
        "color": "#ED1C24",
        "destino": "Santa Laura",
        "sentido": "1",
        "itinerario": false,
        "codigo": "U6"
      }
    ]
  },
  "urlLinkPublicidad": null,
  "urlPublicidad": "http://mkt.smsbus.cl/img/Cat11.jpg",
  "x": "-",
  "y": "-",
  "valid": true,
  "googleMaps": {
    "address_components": [
      {
        "long_name": "Chile",
        "short_name": "CL",
        "types": [
          "country",
          "political"
        ]
      },
      {
        "long_name": "Quilicura",
        "short_name": "Quilicura",
        "types": [
          "locality",
          "political"
        ]
      },
      {
        "long_name": "Quilicura",
        "short_name": "Quilicura",
        "types": [
          "administrative_area_level_3",
          "political"
        ]
      },
      {
        "long_name": "Santiago",
        "short_name": "Santiago",
        "types": [
          "administrative_area_level_2",
          "political"
        ]
      },
      {
        "long_name": "Región Metropolitana",
        "short_name": "Región Metropolitana",
        "types": [
          "administrative_area_level_1",
          "political"
        ]
      }
    ],
    "formatted_address": "Quilicura, Región Metropolitana, Chile",
    "geometry": {
      "location": {
        "lat": -33.3609255,
        "lng": -70.7311361
      },
      "location_type": "GEOMETRIC_CENTER",
      "viewport": {
        "northeast": {
          "lat": -33.3595765197085,
          "lng": -70.72978711970849
        },
        "southwest": {
          "lat": -33.3622744802915,
          "lng": -70.73248508029151
        }
      }
    },
    "place_id": "ChIJaTYJJcXAYpYR_Hr28_-8nsE",
    "types": [
      "bus_station",
      "establishment",
      "point_of_interest",
      "transit_station"
    ]
  },
  "lat": -33.3609255,
  "lng": -70.7311361
}