{
  "fechaprediccion": "2017-08-01",
  "horaprediccion": "13:38",
  "nomett": "AVENIDA TOMAS MORO ESQ. / MONROE",
  "paradero": "PC124",
  "respuestaParadero": "",
  "servicios": {
    "item": [
      {
        "codigorespuesta": "00",
        "distanciabus1": "2238",
        "distanciabus2": "2948",
        "horaprediccionbus1": "Entre 06 Y 10 min. ",
        "horaprediccionbus2": "Entre 09 Y 15 min. ",
        "ppubus1": "ZN-6007",
        "ppubus2": "ZN-5803",
        "respuestaServicio": "",
        "servicio": "401",
        "color": "#F7941D",
        "destino": "Las Condes",
        "sentido": "1",
        "itinerario": false,
        "codigo": "U4"
      },
      {
        "codigorespuesta": "00",
        "distanciabus1": "537",
        "distanciabus2": "1977",
        "horaprediccionbus1": "Menos de 5 min.",
        "horaprediccionbus2": "Entre 05 Y 09 min. ",
        "ppubus1": "ZN-6043",
        "ppubus2": "CJRT-29",
        "respuestaServicio": "",
        "servicio": "427",
        "color": "#F7941D",
        "destino": "Vital Apoquindo",
        "sentido": "1",
        "itinerario": false,
        "codigo": "U4"
      },
      {
        "codigorespuesta": "00",
        "distanciabus1": "3568",
        "distanciabus2": "4788",
        "horaprediccionbus1": "Entre 08 Y 12 min. ",
        "horaprediccionbus2": "Entre 09 Y 15 min. ",
        "ppubus1": "MX-4326",
        "ppubus2": "MY-3915",
        "respuestaServicio": "",
        "servicio": "C05",
        "color": "#ED1C24",
        "destino": "Metro Francisco Bilbao",
        "sentido": "1",
        "itinerario": false,
        "codigo": "U6"
      }
    ]
  },
  "urlLinkPublicidad": null,
  "urlPublicidad": "http://mkt.smsbus.cl/img/Cat11.jpg",
  "x": "-",
  "y": "-",
  "valid": true,
  "googleMaps": {
    "address_components": [
      {
        "long_name": "Chile",
        "short_name": "CL",
        "types": [
          "country",
          "political"
        ]
      },
      {
        "long_name": "Las Condes",
        "short_name": "Las Condes",
        "types": [
          "locality",
          "political"
        ]
      },
      {
        "long_name": "Las Condes",
        "short_name": "Las Condes",
        "types": [
          "administrative_area_level_3",
          "political"
        ]
      },
      {
        "long_name": "Santiago",
        "short_name": "Santiago",
        "types": [
          "administrative_area_level_2",
          "political"
        ]
      },
      {
        "long_name": "Región Metropolitana",
        "short_name": "Región Metropolitana",
        "types": [
          "administrative_area_level_1",
          "political"
        ]
      }
    ],
    "formatted_address": "Las Condes, Región Metropolitana, Chile",
    "geometry": {
      "location": {
        "lat": -33.4147768,
        "lng": -70.552819
      },
      "location_type": "GEOMETRIC_CENTER",
      "viewport": {
        "northeast": {
          "lat": -33.4134278197085,
          "lng": -70.5514700197085
        },
        "southwest": {
          "lat": -33.4161257802915,
          "lng": -70.55416798029151
        }
      }
    },
    "place_id": "ChIJfULBjuzOYpYRDtfF1H4VFNI",
    "types": [
      "bus_station",
      "establishment",
      "point_of_interest",
      "transit_station"
    ]
  },
  "lat": -33.4147768,
  "lng": -70.552819
}