{
  "fechaprediccion": "2017-08-01",
  "horaprediccion": "13:35",
  "nomett": "LAS HUALTATAS ESQ. / TEXAS",
  "paradero": "PC880",
  "respuestaParadero": "",
  "servicios": {
    "item": [
      {
        "codigorespuesta": "00",
        "distanciabus1": "473",
        "distanciabus2": "993",
        "horaprediccionbus1": "Menos de 5 min.",
        "horaprediccionbus2": "Menos de 5 min.",
        "ppubus1": "MZ-8071",
        "ppubus2": "CJRT-61",
        "respuestaServicio": "",
        "servicio": "C11",
        "color": "#ED1C24",
        "destino": "Tabancura",
        "sentido": "1",
        "itinerario": false,
        "codigo": "U6"
      }
    ]
  },
  "urlLinkPublicidad": null,
  "urlPublicidad": "http://mkt.smsbus.cl/img/Cat11.jpg",
  "x": "-",
  "y": "-",
  "valid": true,
  "googleMaps": {
    "address_components": [
      {
        "long_name": "Chile",
        "short_name": "CL",
        "types": [
          "country",
          "political"
        ]
      },
      {
        "long_name": "Vitacura",
        "short_name": "Vitacura",
        "types": [
          "locality",
          "political"
        ]
      },
      {
        "long_name": "Vitacura",
        "short_name": "Vitacura",
        "types": [
          "administrative_area_level_3",
          "political"
        ]
      },
      {
        "long_name": "Santiago",
        "short_name": "Santiago",
        "types": [
          "administrative_area_level_2",
          "political"
        ]
      },
      {
        "long_name": "Región Metropolitana",
        "short_name": "Región Metropolitana",
        "types": [
          "administrative_area_level_1",
          "political"
        ]
      }
    ],
    "formatted_address": "Vitacura, Región Metropolitana, Chile",
    "geometry": {
      "location": {
        "lat": -33.3904417,
        "lng": -70.559911
      },
      "location_type": "GEOMETRIC_CENTER",
      "viewport": {
        "northeast": {
          "lat": -33.38909271970849,
          "lng": -70.5585620197085
        },
        "southwest": {
          "lat": -33.39179068029149,
          "lng": -70.56125998029151
        }
      }
    },
    "place_id": "ChIJw3gPBs3OYpYRkHs7zaa0KEU",
    "types": [
      "bus_station",
      "establishment",
      "point_of_interest",
      "transit_station"
    ]
  },
  "lat": -33.3904417,
  "lng": -70.559911
}