{
  "fechaprediccion": "2017-08-01",
  "horaprediccion": "13:30",
  "nomett": "EL LIBANO ESQ. / LOS OLMOS",
  "paradero": "PD637",
  "respuestaParadero": "",
  "servicios": {
    "item": [
      {
        "codigorespuesta": "00",
        "distanciabus1": "3131",
        "distanciabus2": "9481",
        "horaprediccionbus1": "Entre 06 Y 10 min. ",
        "horaprediccionbus2": "Entre 22 Y 32 min. ",
        "ppubus1": "BJFS-45",
        "ppubus2": "BJFT-10",
        "respuestaServicio": "",
        "servicio": "325",
        "color": "#00A77E",
        "destino": "Metro Irarr치zaval",
        "sentido": "1",
        "itinerario": false,
        "codigo": "U3"
      },
      {
        "codigorespuesta": "01",
        "distanciabus1": "1550",
        "distanciabus2": null,
        "horaprediccionbus1": "Menos de 5 min.",
        "horaprediccionbus2": null,
        "ppubus1": "CJRX-76",
        "ppubus2": null,
        "respuestaServicio": "",
        "servicio": "D16",
        "color": "#F7941D",
        "destino": "Metro Francisco Bilbao",
        "sentido": "1",
        "itinerario": false,
        "codigo": "U4"
      },
      {
        "codigorespuesta": "00",
        "distanciabus1": "1162",
        "distanciabus2": "4632",
        "horaprediccionbus1": "Menos de 5 min.",
        "horaprediccionbus2": "Entre 09 Y 15 min. ",
        "ppubus1": "BJFF-46",
        "ppubus2": "BJFH-27",
        "respuestaServicio": "",
        "servicio": "508",
        "color": "#0093B3",
        "destino": "Av. Mapocho",
        "sentido": "2",
        "itinerario": false,
        "codigo": "U5"
      }
    ]
  },
  "urlLinkPublicidad": null,
  "urlPublicidad": "http://mkt.smsbus.cl/img/Cat11.jpg",
  "x": "-",
  "y": "-",
  "valid": true,
  "googleMaps": {
    "address_components": [
      {
        "long_name": "Chile",
        "short_name": "CL",
        "types": [
          "country",
          "political"
        ]
      },
      {
        "long_name": "Macul",
        "short_name": "Macul",
        "types": [
          "locality",
          "political"
        ]
      },
      {
        "long_name": "Macul",
        "short_name": "Macul",
        "types": [
          "administrative_area_level_3",
          "political"
        ]
      },
      {
        "long_name": "Santiago",
        "short_name": "Santiago",
        "types": [
          "administrative_area_level_2",
          "political"
        ]
      },
      {
        "long_name": "Regi칩n Metropolitana",
        "short_name": "Regi칩n Metropolitana",
        "types": [
          "administrative_area_level_1",
          "political"
        ]
      }
    ],
    "formatted_address": "Macul, Regi칩n Metropolitana, Chile",
    "geometry": {
      "location": {
        "lat": -33.4800603,
        "lng": -70.5884647
      },
      "location_type": "GEOMETRIC_CENTER",
      "viewport": {
        "northeast": {
          "lat": -33.4787113197085,
          "lng": -70.58711571970849
        },
        "southwest": {
          "lat": -33.4814092802915,
          "lng": -70.58981368029151
        }
      }
    },
    "place_id": "ChIJXYLPmCfQYpYRcvuE3zY8Vwc",
    "types": [
      "bus_station",
      "establishment",
      "point_of_interest",
      "transit_station"
    ]
  },
  "lat": -33.4800603,
  "lng": -70.5884647
}