{
  "fechaprediccion": "2017-08-01",
  "horaprediccion": "13:21",
  "nomett": "PARADA  / PARADERO 11   AV.VICUNA MACKENNA",
  "paradero": "PE122",
  "respuestaParadero": "",
  "servicios": {
    "item": [
      {
        "codigorespuesta": "00",
        "distanciabus1": "316",
        "distanciabus2": "436",
        "horaprediccionbus1": "Menos de 5 min.",
        "horaprediccionbus2": "Menos de 5 min.",
        "ppubus1": "ZN-5610",
        "ppubus2": "BJFF-25",
        "respuestaServicio": "",
        "servicio": "210",
        "color": "#0077bb",
        "destino": "Puente Alto",
        "sentido": "1",
        "itinerario": true,
        "codigo": "U2"
      },
      {
        "codigorespuesta": "00",
        "distanciabus1": "546",
        "distanciabus2": "2466",
        "horaprediccionbus1": "Menos de 5 min.",
        "horaprediccionbus2": "Entre 03 Y 07 min. ",
        "ppubus1": "BJFK-63",
        "ppubus2": "BJFD-96",
        "respuestaServicio": "",
        "servicio": "210V",
        "color": "#0077bb",
        "destino": "Av. Mexico",
        "sentido": "1",
        "itinerario": false,
        "codigo": "U2"
      },
      {
        "codigorespuesta": "00",
        "distanciabus1": "1575",
        "distanciabus2": "3795",
        "horaprediccionbus1": "Menos de 5 min.",
        "horaprediccionbus2": "Entre 06 Y 10 min. ",
        "ppubus1": "BJFF-30",
        "ppubus2": "BJFK-61",
        "respuestaServicio": "",
        "servicio": "224",
        "color": "#0077bb",
        "destino": "Gabriela",
        "sentido": "1",
        "itinerario": false,
        "codigo": "U2"
      },
      {
        "codigorespuesta": "00",
        "distanciabus1": "3114",
        "distanciabus2": "6044",
        "horaprediccionbus1": "Entre 08 Y 14 min. ",
        "horaprediccionbus2": "Entre 18 Y 28 min. ",
        "ppubus1": "BJFS-32",
        "ppubus2": "BJFV-27",
        "respuestaServicio": "",
        "servicio": "E04",
        "color": "#00A77E",
        "destino": "Av. La Florida",
        "sentido": "2",
        "itinerario": false,
        "codigo": "U3"
      },
      {
        "codigorespuesta": "11",
        "distanciabus1": null,
        "distanciabus2": null,
        "horaprediccionbus1": null,
        "horaprediccionbus2": null,
        "ppubus1": null,
        "ppubus2": null,
        "respuestaServicio": "Fuera de horario de operacion para este paradero",
        "servicio": "E05",
        "color": "#00A77E",
        "destino": "Metro B. de La Florida",
        "sentido": "1",
        "itinerario": false,
        "codigo": "U3"
      },
      {
        "codigorespuesta": "9",
        "distanciabus1": null,
        "distanciabus2": null,
        "horaprediccionbus1": null,
        "horaprediccionbus2": null,
        "ppubus1": null,
        "ppubus2": null,
        "respuestaServicio": "Frecuencia estimada es 1 bus cada 11 min.",
        "servicio": "385",
        "color": null,
        "destino": null,
        "sentido": null,
        "itinerario": null,
        "codigo": null
      },
      {
        "codigorespuesta": "11",
        "distanciabus1": null,
        "distanciabus2": null,
        "horaprediccionbus1": null,
        "horaprediccionbus2": null,
        "ppubus1": null,
        "ppubus2": null,
        "respuestaServicio": "Fuera de horario de operacion para este paradero",
        "servicio": "F30N",
        "color": "#FFD400",
        "destino": "Bajos De Mena",
        "sentido": "2",
        "itinerario": true,
        "codigo": "U7"
      }
    ]
  },
  "urlLinkPublicidad": null,
  "urlPublicidad": "http://mkt.smsbus.cl/img/Cat11.jpg",
  "x": "-",
  "y": "-",
  "valid": true,
  "googleMaps": {
    "address_components": [
      {
        "long_name": "Chile",
        "short_name": "CL",
        "types": [
          "country",
          "political"
        ]
      },
      {
        "long_name": "La Florida",
        "short_name": "La Florida",
        "types": [
          "locality",
          "political"
        ]
      },
      {
        "long_name": "La Florida",
        "short_name": "La Florida",
        "types": [
          "administrative_area_level_3",
          "political"
        ]
      },
      {
        "long_name": "Santiago",
        "short_name": "Santiago",
        "types": [
          "administrative_area_level_2",
          "political"
        ]
      },
      {
        "long_name": "Región Metropolitana",
        "short_name": "Región Metropolitana",
        "types": [
          "administrative_area_level_1",
          "political"
        ]
      }
    ],
    "formatted_address": "La Florida, Región Metropolitana, Chile",
    "geometry": {
      "location": {
        "lat": -33.51555889999999,
        "lng": -70.60688429999999
      },
      "location_type": "GEOMETRIC_CENTER",
      "viewport": {
        "northeast": {
          "lat": -33.51420991970849,
          "lng": -70.60553531970848
        },
        "southwest": {
          "lat": -33.51690788029149,
          "lng": -70.60823328029149
        }
      }
    },
    "place_id": "ChIJrYavCmXQYpYRhPQwYsYqBHA",
    "types": [
      "bus_station",
      "establishment",
      "point_of_interest",
      "transit_station"
    ]
  },
  "lat": -33.51555889999999,
  "lng": -70.60688429999999
}