{
  "fechaprediccion": "2017-08-01",
  "horaprediccion": "13:13",
  "nomett": "PHILIPPE COUSTEAU ESQ. / CAMINO LA VARA",
  "paradero": "PG1058",
  "respuestaParadero": "",
  "servicios": {
    "item": [
      {
        "codigorespuesta": "00",
        "distanciabus1": "1802",
        "distanciabus2": "5812",
        "horaprediccionbus1": "Entre 04 Y 08 min. ",
        "horaprediccionbus2": "Entre 15 Y 23 min. ",
        "ppubus1": "CJRP-70",
        "ppubus2": "CJRR-60",
        "respuestaServicio": "",
        "servicio": "G09",
        "color": "#0077bb",
        "destino": "Lo Blanco",
        "sentido": "2",
        "itinerario": false,
        "codigo": "U2"
      }
    ]
  },
  "urlLinkPublicidad": null,
  "urlPublicidad": "http://mkt.smsbus.cl/img/Cat11.jpg",
  "x": "-",
  "y": "-",
  "valid": true,
  "googleMaps": {
    "address_components": [
      {
        "long_name": "Chile",
        "short_name": "CL",
        "types": [
          "country",
          "political"
        ]
      },
      {
        "long_name": "San Bernardo",
        "short_name": "San Bernardo",
        "types": [
          "locality",
          "political"
        ]
      },
      {
        "long_name": "San Bernardo",
        "short_name": "San Bernardo",
        "types": [
          "administrative_area_level_3",
          "political"
        ]
      },
      {
        "long_name": "Maipo",
        "short_name": "Maipo",
        "types": [
          "administrative_area_level_2",
          "political"
        ]
      },
      {
        "long_name": "Región Metropolitana",
        "short_name": "Región Metropolitana",
        "types": [
          "administrative_area_level_1",
          "political"
        ]
      }
    ],
    "formatted_address": "San Bernardo, Región Metropolitana, Chile",
    "geometry": {
      "location": {
        "lat": -33.5665165,
        "lng": -70.701697
      },
      "location_type": "GEOMETRIC_CENTER",
      "viewport": {
        "northeast": {
          "lat": -33.5651675197085,
          "lng": -70.70034801970849
        },
        "southwest": {
          "lat": -33.56786548029149,
          "lng": -70.7030459802915
        }
      }
    },
    "partial_match": true,
    "place_id": "ChIJa903MuzbYpYRtpxLC4sQT1g",
    "types": [
      "bus_station",
      "establishment",
      "point_of_interest",
      "transit_station"
    ]
  },
  "lat": -33.5665165,
  "lng": -70.701697
}