{
  "fechaprediccion": "2017-07-31",
  "horaprediccion": "18:38",
  "nomett": "AVENIDA LO ESPEJO ESQ. / CAMINO PRIVADO",
  "paradero": "PG1462",
  "respuestaParadero": "No hay buses que se dirijan al paradero.",
  "servicios": {
    "item": [
      {
        "codigorespuesta": "10",
        "distanciabus1": null,
        "distanciabus2": null,
        "horaprediccionbus1": null,
        "horaprediccionbus2": null,
        "ppubus1": null,
        "ppubus2": null,
        "respuestaServicio": "No hay buses que se dirijan al paradero.",
        "servicio": "329",
        "color": "#00A77E",
        "destino": "Mall Florida Center",
        "sentido": "1",
        "itinerario": false,
        "codigo": "U3"
      },
      {
        "codigorespuesta": "10",
        "distanciabus1": null,
        "distanciabus2": null,
        "horaprediccionbus1": null,
        "horaprediccionbus2": null,
        "ppubus1": null,
        "ppubus2": null,
        "respuestaServicio": "No hay buses que se dirijan al paradero.",
        "servicio": "H03",
        "color": "#00A77E",
        "destino": "Metro Lo Ovalle",
        "sentido": "2",
        "itinerario": false,
        "codigo": "U3"
      },
      {
        "codigorespuesta": "10",
        "distanciabus1": null,
        "distanciabus2": null,
        "horaprediccionbus1": null,
        "horaprediccionbus2": null,
        "ppubus1": null,
        "ppubus2": null,
        "respuestaServicio": "No hay buses que se dirijan al paradero.",
        "servicio": "I12",
        "color": null,
        "destino": null,
        "sentido": null,
        "itinerario": null,
        "codigo": null
      }
    ]
  },
  "urlLinkPublicidad": null,
  "urlPublicidad": "http://mkt.smsbus.cl/img/Cat11.jpg",
  "x": "-",
  "y": "-",
  "valid": true,
  "googleMaps": {
    "address_components": [
      {
        "long_name": "Chile",
        "short_name": "CL",
        "types": [
          "country",
          "political"
        ]
      },
      {
        "long_name": "San Bernardo",
        "short_name": "San Bernardo",
        "types": [
          "locality",
          "political"
        ]
      },
      {
        "long_name": "San Bernardo",
        "short_name": "San Bernardo",
        "types": [
          "administrative_area_level_3",
          "political"
        ]
      },
      {
        "long_name": "Maipo",
        "short_name": "Maipo",
        "types": [
          "administrative_area_level_2",
          "political"
        ]
      },
      {
        "long_name": "Región Metropolitana",
        "short_name": "Región Metropolitana",
        "types": [
          "administrative_area_level_1",
          "political"
        ]
      }
    ],
    "formatted_address": "San Bernardo, Región Metropolitana, Chile",
    "geometry": {
      "location": {
        "lat": -33.5309644,
        "lng": -70.707625
      },
      "location_type": "GEOMETRIC_CENTER",
      "viewport": {
        "northeast": {
          "lat": -33.5296154197085,
          "lng": -70.70627601970848
        },
        "southwest": {
          "lat": -33.5323133802915,
          "lng": -70.70897398029149
        }
      }
    },
    "place_id": "ChIJMcy-1nrbYpYRHcHgLNf0N4M",
    "types": [
      "bus_station",
      "establishment",
      "point_of_interest",
      "transit_station"
    ]
  },
  "lat": -33.5309644,
  "lng": -70.707625
}