{
  "fechaprediccion": "2017-07-31",
  "horaprediccion": "18:35",
  "nomett": "CAMINO EL MARISCAL ESQ. / AV. PADRE HURTADO",
  "paradero": "PG517",
  "respuestaParadero": "",
  "servicios": {
    "item": [
      {
        "codigorespuesta": "00",
        "distanciabus1": "768",
        "distanciabus2": "1078",
        "horaprediccionbus1": "Entre 05 Y 09 min. ",
        "horaprediccionbus2": "Entre 08 Y 12 min. ",
        "ppubus1": "CJRB-53",
        "ppubus2": "FLXT-47",
        "respuestaServicio": "",
        "servicio": "F03",
        "color": "#FFD400",
        "destino": "Plaza San Bernardo",
        "sentido": "1",
        "itinerario": false,
        "codigo": "U7"
      }
    ]
  },
  "urlLinkPublicidad": null,
  "urlPublicidad": "http://mkt.smsbus.cl/img/Cat11.jpg",
  "x": "-",
  "y": "-",
  "valid": true,
  "googleMaps": {
    "address_components": [
      {
        "long_name": "Chile",
        "short_name": "CL",
        "types": [
          "country",
          "political"
        ]
      },
      {
        "long_name": "San Bernardo",
        "short_name": "San Bernardo",
        "types": [
          "locality",
          "political"
        ]
      },
      {
        "long_name": "San Bernardo",
        "short_name": "San Bernardo",
        "types": [
          "administrative_area_level_3",
          "political"
        ]
      },
      {
        "long_name": "Maipo",
        "short_name": "Maipo",
        "types": [
          "administrative_area_level_2",
          "political"
        ]
      },
      {
        "long_name": "Región Metropolitana",
        "short_name": "Región Metropolitana",
        "types": [
          "administrative_area_level_1",
          "political"
        ]
      }
    ],
    "formatted_address": "San Bernardo, Región Metropolitana, Chile",
    "geometry": {
      "location": {
        "lat": -33.6049098,
        "lng": -70.682226
      },
      "location_type": "GEOMETRIC_CENTER",
      "viewport": {
        "northeast": {
          "lat": -33.6035608197085,
          "lng": -70.6808770197085
        },
        "southwest": {
          "lat": -33.6062587802915,
          "lng": -70.68357498029151
        }
      }
    },
    "partial_match": true,
    "place_id": "ChIJy-X3YxLZYpYRq594oL68C50",
    "types": [
      "bus_station",
      "establishment",
      "point_of_interest",
      "transit_station"
    ]
  },
  "lat": -33.6049098,
  "lng": -70.682226
}