{
  "fechaprediccion": "2017-07-31",
  "horaprediccion": "18:33",
  "nomett": "AV. SAN FRANCISCO ESQ. / AVENIDA LO BLANCO",
  "paradero": "PG950",
  "respuestaParadero": "Frecuencia estimada es 1 bus cada 4 min.",
  "servicios": {
    "item": [
      {
        "codigorespuesta": "9",
        "distanciabus1": null,
        "distanciabus2": null,
        "horaprediccionbus1": null,
        "horaprediccionbus2": null,
        "ppubus1": null,
        "ppubus2": null,
        "respuestaServicio": "Frecuencia estimada es 1 bus cada 4 min.",
        "servicio": "203",
        "color": "#0077bb",
        "destino": "Huechuraba",
        "sentido": "2",
        "itinerario": false,
        "codigo": "U2"
      },
      {
        "codigorespuesta": "9",
        "distanciabus1": null,
        "distanciabus2": null,
        "horaprediccionbus1": null,
        "horaprediccionbus2": null,
        "ppubus1": null,
        "ppubus2": null,
        "respuestaServicio": "Frecuencia estimada es 1 bus cada 6 min.",
        "servicio": "203E",
        "color": "#0077bb",
        "destino": "Centro",
        "sentido": "2",
        "itinerario": false,
        "codigo": "U2"
      },
      {
        "codigorespuesta": "9",
        "distanciabus1": null,
        "distanciabus2": null,
        "horaprediccionbus1": null,
        "horaprediccionbus2": null,
        "ppubus1": null,
        "ppubus2": null,
        "respuestaServicio": "Frecuencia estimada es 1 bus cada 10 min.",
        "servicio": "206",
        "color": "#0077bb",
        "destino": "Centro",
        "sentido": "2",
        "itinerario": false,
        "codigo": "U2"
      },
      {
        "codigorespuesta": "9",
        "distanciabus1": null,
        "distanciabus2": null,
        "horaprediccionbus1": null,
        "horaprediccionbus2": null,
        "ppubus1": null,
        "ppubus2": null,
        "respuestaServicio": "Frecuencia estimada es 1 bus cada 12 min.",
        "servicio": "206E",
        "color": "#0077bb",
        "destino": "Centro",
        "sentido": "2",
        "itinerario": false,
        "codigo": "U2"
      },
      {
        "codigorespuesta": "00",
        "distanciabus1": "2",
        "distanciabus2": "452",
        "horaprediccionbus1": "Menos de 5 min.",
        "horaprediccionbus2": "Menos de 5 min.",
        "ppubus1": "ZW-5079",
        "ppubus2": "ZW-5082",
        "respuestaServicio": "",
        "servicio": "228",
        "color": "#0077bb",
        "destino": "Metro La Cisterna",
        "sentido": "2",
        "itinerario": false,
        "codigo": "U2"
      },
      {
        "codigorespuesta": "9",
        "distanciabus1": null,
        "distanciabus2": null,
        "horaprediccionbus1": null,
        "horaprediccionbus2": null,
        "ppubus1": null,
        "ppubus2": null,
        "respuestaServicio": "Frecuencia estimada es 1 bus cada 11 min.",
        "servicio": "229",
        "color": "#0077bb",
        "destino": "Metro La Moneda",
        "sentido": "2",
        "itinerario": false,
        "codigo": "U2"
      },
      {
        "codigorespuesta": "00",
        "distanciabus1": "2336",
        "distanciabus2": "4736",
        "horaprediccionbus1": "Entre 06 Y 10 min. ",
        "horaprediccionbus2": "Entre 12 Y 20 min. ",
        "ppubus1": "CJRL-65",
        "ppubus2": "ZN-6293",
        "respuestaServicio": "",
        "servicio": "G08",
        "color": "#0077bb",
        "destino": "Metro La Cisterna",
        "sentido": "1",
        "itinerario": false,
        "codigo": "U2"
      },
      {
        "codigorespuesta": "00",
        "distanciabus1": "3290",
        "distanciabus2": "6890",
        "horaprediccionbus1": "Entre 08 Y 14 min. ",
        "horaprediccionbus2": "Entre 20 Y 30 min. ",
        "ppubus1": "BJFD-94",
        "ppubus2": "CJRP-53",
        "respuestaServicio": "",
        "servicio": "G09",
        "color": "#0077bb",
        "destino": "Lo Blanco",
        "sentido": "2",
        "itinerario": false,
        "codigo": "U2"
      }
    ]
  },
  "urlLinkPublicidad": null,
  "urlPublicidad": "http://mkt.smsbus.cl/img/Cat11.jpg",
  "x": "-",
  "y": "-",
  "valid": true,
  "googleMaps": {
    "address_components": [
      {
        "long_name": "Chile",
        "short_name": "CL",
        "types": [
          "country",
          "political"
        ]
      },
      {
        "long_name": "La Pintana",
        "short_name": "La Pintana",
        "types": [
          "locality",
          "political"
        ]
      },
      {
        "long_name": "La Pintana",
        "short_name": "La Pintana",
        "types": [
          "administrative_area_level_3",
          "political"
        ]
      },
      {
        "long_name": "Santiago",
        "short_name": "Santiago",
        "types": [
          "administrative_area_level_2",
          "political"
        ]
      },
      {
        "long_name": "Región Metropolitana",
        "short_name": "Región Metropolitana",
        "types": [
          "administrative_area_level_1",
          "political"
        ]
      }
    ],
    "formatted_address": "La Pintana, Región Metropolitana, Chile",
    "geometry": {
      "location": {
        "lat": -33.5854411,
        "lng": -70.663298
      },
      "location_type": "GEOMETRIC_CENTER",
      "viewport": {
        "northeast": {
          "lat": -33.58409211970849,
          "lng": -70.66194901970849
        },
        "southwest": {
          "lat": -33.58679008029149,
          "lng": -70.6646469802915
        }
      }
    },
    "place_id": "ChIJJVsfgITZYpYRsTSk4f9PY-w",
    "types": [
      "bus_station",
      "establishment",
      "point_of_interest",
      "transit_station"
    ]
  },
  "lat": -33.5854411,
  "lng": -70.663298
}