{
  "fechaprediccion": "2017-07-31",
  "horaprediccion": "15:50",
  "nomett": "PARADA  / P. AGUIRRE CERDA   ALTURA DEL 5800",
  "paradero": "PI1618",
  "respuestaParadero": "",
  "servicios": {
    "item": [
      {
        "codigorespuesta": "00",
        "distanciabus1": "1233",
        "distanciabus2": "3423",
        "horaprediccionbus1": "Menos de 5 min.",
        "horaprediccionbus2": "Entre 07 Y 13 min. ",
        "ppubus1": "ZN-5645",
        "ppubus2": "ZN-6543",
        "respuestaServicio": "",
        "servicio": "108",
        "color": "#00A1E4",
        "destino": "Maipú",
        "sentido": "2",
        "itinerario": false,
        "codigo": "U1"
      },
      {
        "codigorespuesta": "00",
        "distanciabus1": "620",
        "distanciabus2": "4650",
        "horaprediccionbus1": "Menos de 5 min.",
        "horaprediccionbus2": "Entre 07 Y 13 min. ",
        "ppubus1": "ZN-3954",
        "ppubus2": "ZN-5401",
        "respuestaServicio": "",
        "servicio": "109",
        "color": "#00A1E4",
        "destino": "Maipú",
        "sentido": "1",
        "itinerario": false,
        "codigo": "U1"
      },
      {
        "codigorespuesta": "11",
        "distanciabus1": null,
        "distanciabus2": null,
        "horaprediccionbus1": null,
        "horaprediccionbus2": null,
        "ppubus1": null,
        "ppubus2": null,
        "respuestaServicio": "Fuera de horario de operacion para este paradero",
        "servicio": "109N",
        "color": "#00A1E4",
        "destino": "Maipú",
        "sentido": "1",
        "itinerario": false,
        "codigo": "U1"
      },
      {
        "codigorespuesta": "00",
        "distanciabus1": "1185",
        "distanciabus2": "5275",
        "horaprediccionbus1": "Menos de 5 min.",
        "horaprediccionbus2": "Entre 11 Y 17 min. ",
        "ppubus1": "ZN-4321",
        "ppubus2": "ZN-3952",
        "respuestaServicio": "",
        "servicio": "113",
        "color": "#00A1E4",
        "destino": "Ciudad Satélite",
        "sentido": "2",
        "itinerario": false,
        "codigo": "U1"
      },
      {
        "codigorespuesta": "00",
        "distanciabus1": "3735",
        "distanciabus2": "5215",
        "horaprediccionbus1": "Entre 07 Y 11 min. ",
        "horaprediccionbus2": "Entre 12 Y 18 min. ",
        "ppubus1": "WA-9900",
        "ppubus2": "ZN-3964",
        "respuestaServicio": "",
        "servicio": "115",
        "color": "#00A1E4",
        "destino": "Villa El Abrazo",
        "sentido": "2",
        "itinerario": false,
        "codigo": "U1"
      }
    ]
  },
  "urlLinkPublicidad": null,
  "urlPublicidad": "http://mkt.smsbus.cl/img/Cat11.jpg",
  "x": "-",
  "y": "-",
  "valid": true,
  "googleMaps": {
    "address_components": [
      {
        "long_name": "Chile",
        "short_name": "CL",
        "types": [
          "country",
          "political"
        ]
      },
      {
        "long_name": "Los Cerrillos",
        "short_name": "Los Cerrillos",
        "types": [
          "locality",
          "political"
        ]
      },
      {
        "long_name": "Cerrillos",
        "short_name": "Cerrillos",
        "types": [
          "administrative_area_level_3",
          "political"
        ]
      },
      {
        "long_name": "Santiago",
        "short_name": "Santiago",
        "types": [
          "administrative_area_level_2",
          "political"
        ]
      },
      {
        "long_name": "Región Metropolitana",
        "short_name": "Región Metropolitana",
        "types": [
          "administrative_area_level_1",
          "political"
        ]
      }
    ],
    "formatted_address": "Los Cerrillos, Cerrillos, Región Metropolitana, Chile",
    "geometry": {
      "location": {
        "lat": -33.4915597,
        "lng": -70.7030154
      },
      "location_type": "GEOMETRIC_CENTER",
      "viewport": {
        "northeast": {
          "lat": -33.49021071970849,
          "lng": -70.70166641970849
        },
        "southwest": {
          "lat": -33.49290868029149,
          "lng": -70.70436438029151
        }
      }
    },
    "place_id": "ChIJkxBhjrHEYpYRv2LX0XC8M1c",
    "types": [
      "bus_station",
      "establishment",
      "point_of_interest",
      "transit_station"
    ]
  },
  "lat": -33.4915597,
  "lng": -70.7030154
}