{
  "fechaprediccion": "2017-07-31",
  "horaprediccion": "15:48",
  "nomett": "PARADA 1 / LICEO A70",
  "paradero": "PI38",
  "respuestaParadero": "",
  "servicios": {
    "item": [
      {
        "codigorespuesta": "00",
        "distanciabus1": "2352",
        "distanciabus2": "5062",
        "horaprediccionbus1": "Entre 05 Y 09 min. ",
        "horaprediccionbus2": "Entre 12 Y 18 min. ",
        "ppubus1": "BJFD-38",
        "ppubus2": "CJRF-59",
        "respuestaServicio": "",
        "servicio": "101",
        "color": "#00A1E4",
        "destino": "Recoleta",
        "sentido": "2",
        "itinerario": false,
        "codigo": "U1"
      },
      {
        "codigorespuesta": "11",
        "distanciabus1": null,
        "distanciabus2": null,
        "horaprediccionbus1": null,
        "horaprediccionbus2": null,
        "ppubus1": null,
        "ppubus2": null,
        "respuestaServicio": "Fuera de horario de operacion para este paradero",
        "servicio": "101C",
        "color": "#00A1E4",
        "destino": "Metro Las Rejas",
        "sentido": "2",
        "itinerario": false,
        "codigo": "U1"
      },
      {
        "codigorespuesta": "00",
        "distanciabus1": "283",
        "distanciabus2": "3423",
        "horaprediccionbus1": "Menos de 5 min.",
        "horaprediccionbus2": "Entre 08 Y 14 min. ",
        "ppubus1": "FLXK-14",
        "ppubus2": "FLXJ-48",
        "respuestaServicio": "",
        "servicio": "I04",
        "color": "#00A77E",
        "destino": "Metro Sn. A. Hurtado",
        "sentido": "1",
        "itinerario": false,
        "codigo": "U3"
      },
      {
        "codigorespuesta": "00",
        "distanciabus1": "3323",
        "distanciabus2": "4763",
        "horaprediccionbus1": "Entre 08 Y 12 min. ",
        "horaprediccionbus2": "Entre 13 Y 21 min. ",
        "ppubus1": "FLXG-98",
        "ppubus2": "FLXG-91",
        "respuestaServicio": "",
        "servicio": "I10",
        "color": "#00A77E",
        "destino": "USACH",
        "sentido": "1",
        "itinerario": false,
        "codigo": "U3"
      },
      {
        "codigorespuesta": "11",
        "distanciabus1": null,
        "distanciabus2": null,
        "horaprediccionbus1": null,
        "horaprediccionbus2": null,
        "ppubus1": null,
        "ppubus2": null,
        "respuestaServicio": "Fuera de horario de operacion para este paradero",
        "servicio": "I10N",
        "color": "#00A77E",
        "destino": "Alameda",
        "sentido": "1",
        "itinerario": false,
        "codigo": "U3"
      },
      {
        "codigorespuesta": "10",
        "distanciabus1": null,
        "distanciabus2": null,
        "horaprediccionbus1": null,
        "horaprediccionbus2": null,
        "ppubus1": null,
        "ppubus2": null,
        "respuestaServicio": "No hay buses que se dirijan al paradero.",
        "servicio": "I13",
        "color": "#00A77E",
        "destino": "Metro Sn. A. Hurtado",
        "sentido": "1",
        "itinerario": false,
        "codigo": "U3"
      },
      {
        "codigorespuesta": "00",
        "distanciabus1": "2077",
        "distanciabus2": "7157",
        "horaprediccionbus1": "Entre 04 Y 08 min. ",
        "horaprediccionbus2": "Entre 18 Y 28 min. ",
        "ppubus1": "CJRW-66",
        "ppubus2": "CJRW-77",
        "respuestaServicio": "",
        "servicio": "I14",
        "color": "#00A77E",
        "destino": "Estación Central",
        "sentido": "1",
        "itinerario": false,
        "codigo": "U3"
      },
      {
        "codigorespuesta": "10",
        "distanciabus1": null,
        "distanciabus2": null,
        "horaprediccionbus1": null,
        "horaprediccionbus2": null,
        "ppubus1": null,
        "ppubus2": null,
        "respuestaServicio": "No hay buses que se dirijan al paradero.",
        "servicio": "385",
        "color": "#00A77E",
        "destino": "Florida Center",
        "sentido": "1",
        "itinerario": false,
        "codigo": "U3"
      },
      {
        "codigorespuesta": "10",
        "distanciabus1": null,
        "distanciabus2": null,
        "horaprediccionbus1": null,
        "horaprediccionbus2": null,
        "ppubus1": null,
        "ppubus2": null,
        "respuestaServicio": "No hay buses que se dirijan al paradero.",
        "servicio": "I17",
        "color": "#00A77E",
        "destino": "Hosp. San Juan De Dios",
        "sentido": "1",
        "itinerario": false,
        "codigo": "U3"
      },
      {
        "codigorespuesta": "00",
        "distanciabus1": "1074",
        "distanciabus2": "4024",
        "horaprediccionbus1": "Menos de 5 min.",
        "horaprediccionbus2": "Entre 11 Y 17 min. ",
        "ppubus1": "FDJX-69",
        "ppubus2": "BJFB-30",
        "respuestaServicio": "",
        "servicio": "506",
        "color": "#0093B3",
        "destino": "Peñalolén",
        "sentido": "1",
        "itinerario": false,
        "codigo": "U5"
      },
      {
        "codigorespuesta": "11",
        "distanciabus1": null,
        "distanciabus2": null,
        "horaprediccionbus1": null,
        "horaprediccionbus2": null,
        "ppubus1": null,
        "ppubus2": null,
        "respuestaServicio": "Fuera de horario de operacion para este paradero",
        "servicio": "506E",
        "color": "#0093B3",
        "destino": "Peñalolén",
        "sentido": "1",
        "itinerario": false,
        "codigo": "U5"
      },
      {
        "codigorespuesta": "00",
        "distanciabus1": "1029",
        "distanciabus2": "6549",
        "horaprediccionbus1": "Menos de 5 min.",
        "horaprediccionbus2": "Entre 13 Y 21 min. ",
        "ppubus1": "BFRT-62",
        "ppubus2": "FDJX-76",
        "respuestaServicio": "",
        "servicio": "506V",
        "color": "#0093B3",
        "destino": "Peñalolén",
        "sentido": "1",
        "itinerario": false,
        "codigo": "U5"
      },
      {
        "codigorespuesta": "00",
        "distanciabus1": "1370",
        "distanciabus2": "4440",
        "horaprediccionbus1": "Menos de 5 min.",
        "horaprediccionbus2": "Entre 10 Y 16 min. ",
        "ppubus1": "BDXR-20",
        "ppubus2": "FLXD-48",
        "respuestaServicio": "",
        "servicio": "509",
        "color": "#0093B3",
        "destino": "Mapocho",
        "sentido": "1",
        "itinerario": false,
        "codigo": "U5"
      }
    ]
  },
  "urlLinkPublicidad": null,
  "urlPublicidad": "http://mkt.smsbus.cl/img/Cat11.jpg",
  "x": "-",
  "y": "-",
  "valid": true,
  "googleMaps": {
    "address_components": [
      {
        "long_name": "Chile",
        "short_name": "CL",
        "types": [
          "country",
          "political"
        ]
      },
      {
        "long_name": "Santiago",
        "short_name": "Santiago",
        "types": [
          "locality",
          "political"
        ]
      },
      {
        "long_name": "Estación Central",
        "short_name": "Estación Central",
        "types": [
          "administrative_area_level_3",
          "political"
        ]
      },
      {
        "long_name": "Santiago",
        "short_name": "Santiago",
        "types": [
          "administrative_area_level_2",
          "political"
        ]
      },
      {
        "long_name": "Región Metropolitana",
        "short_name": "Región Metropolitana",
        "types": [
          "administrative_area_level_1",
          "political"
        ]
      }
    ],
    "formatted_address": "Santiago, Estación Central, Región Metropolitana, Chile",
    "geometry": {
      "location": {
        "lat": -33.4722441,
        "lng": -70.720151
      },
      "location_type": "GEOMETRIC_CENTER",
      "viewport": {
        "northeast": {
          "lat": -33.47089511970849,
          "lng": -70.71880201970849
        },
        "southwest": {
          "lat": -33.47359308029149,
          "lng": -70.72149998029151
        }
      }
    },
    "place_id": "ChIJtcf5y2PDYpYRZpBMjZj1-dY",
    "types": [
      "bus_station",
      "establishment",
      "point_of_interest",
      "transit_station"
    ]
  },
  "lat": -33.4722441,
  "lng": -70.720151
}