{
  "fechaprediccion": "2017-07-31",
  "horaprediccion": "15:45",
  "nomett": "PARADA 2 / SAN PABLO   LA ESTRELLA",
  "paradero": "PJ156",
  "respuestaParadero": "",
  "servicios": {
    "item": [
      {
        "codigorespuesta": "00",
        "distanciabus1": "3477",
        "distanciabus2": "8457",
        "horaprediccionbus1": "Entre 11 Y 17 min. ",
        "horaprediccionbus2": "Mas de 25 min.",
        "ppubus1": "WA-8531",
        "ppubus2": "WH-2096",
        "respuestaServicio": "",
        "servicio": "402",
        "color": "#F7941D",
        "destino": "Pudahuel",
        "sentido": "2",
        "itinerario": false,
        "codigo": "U4"
      },
      {
        "codigorespuesta": "00",
        "distanciabus1": "1765",
        "distanciabus2": "3105",
        "horaprediccionbus1": "Entre 05 Y 09 min. ",
        "horaprediccionbus2": "Entre 09 Y 15 min. ",
        "ppubus1": "ZN-6175",
        "ppubus2": "ZN-6022",
        "respuestaServicio": "",
        "servicio": "406",
        "color": "#F7941D",
        "destino": "Pudahuel",
        "sentido": "2",
        "itinerario": false,
        "codigo": "U4"
      },
      {
        "codigorespuesta": "00",
        "distanciabus1": "46",
        "distanciabus2": "2486",
        "horaprediccionbus1": "Menos de 5 min.",
        "horaprediccionbus2": "Entre 06 Y 10 min. ",
        "ppubus1": "WB-2356",
        "ppubus2": "WB-2464",
        "respuestaServicio": "",
        "servicio": "407",
        "color": "#F7941D",
        "destino": "Enea",
        "sentido": "2",
        "itinerario": false,
        "codigo": "U4"
      },
      {
        "codigorespuesta": "00",
        "distanciabus1": "6523",
        "distanciabus2": "8693",
        "horaprediccionbus1": "Entre 16 Y 26 min. ",
        "horaprediccionbus2": "Mas de 25 min.",
        "ppubus1": "ZN-4776",
        "ppubus2": "CJRX-20",
        "respuestaServicio": "",
        "servicio": "422",
        "color": "#F7941D",
        "destino": "Pob. Teniente Merino",
        "sentido": "2",
        "itinerario": false,
        "codigo": "U4"
      },
      {
        "codigorespuesta": "00",
        "distanciabus1": "1225",
        "distanciabus2": "4095",
        "horaprediccionbus1": "Menos de 5 min.",
        "horaprediccionbus2": "Entre 11 Y 17 min. ",
        "ppubus1": "ZN-5684",
        "ppubus2": "FLXC-77",
        "respuestaServicio": "",
        "servicio": "426",
        "color": "#F7941D",
        "destino": "Pudahuel",
        "sentido": "2",
        "itinerario": false,
        "codigo": "U4"
      },
      {
        "codigorespuesta": "00",
        "distanciabus1": "62",
        "distanciabus2": "2962",
        "horaprediccionbus1": "Menos de 5 min.",
        "horaprediccionbus2": "Entre 11 Y 17 min. ",
        "ppubus1": "CJRV-54",
        "ppubus2": "CJRS-85",
        "respuestaServicio": "",
        "servicio": "427",
        "color": "#F7941D",
        "destino": "Pudahuel",
        "sentido": "2",
        "itinerario": false,
        "codigo": "U4"
      },
      {
        "codigorespuesta": "00",
        "distanciabus1": "88",
        "distanciabus2": "2908",
        "horaprediccionbus1": "Menos de 5 min.",
        "horaprediccionbus2": "Entre 09 Y 15 min. ",
        "ppubus1": "BJFY-77",
        "ppubus2": "BJFX-88",
        "respuestaServicio": "",
        "servicio": "511",
        "color": "#0093B3",
        "destino": "Cerro Navia",
        "sentido": "2",
        "itinerario": false,
        "codigo": "U5"
      },
      {
        "codigorespuesta": "10",
        "distanciabus1": null,
        "distanciabus2": null,
        "horaprediccionbus1": null,
        "horaprediccionbus2": null,
        "ppubus1": null,
        "ppubus2": null,
        "respuestaServicio": "No hay buses que se dirijan al paradero.",
        "servicio": "J15C",
        "color": "#0093B3",
        "destino": "La Alianza",
        "sentido": "2",
        "itinerario": false,
        "codigo": "U5"
      }
    ]
  },
  "urlLinkPublicidad": null,
  "urlPublicidad": "http://mkt.smsbus.cl/img/Cat11.jpg",
  "x": "-",
  "y": "-",
  "valid": true,
  "googleMaps": {
    "address_components": [
      {
        "long_name": "Chile",
        "short_name": "CL",
        "types": [
          "country",
          "political"
        ]
      },
      {
        "long_name": "Pudahuel",
        "short_name": "Pudahuel",
        "types": [
          "locality",
          "political"
        ]
      },
      {
        "long_name": "Pudahuel",
        "short_name": "Pudahuel",
        "types": [
          "administrative_area_level_3",
          "political"
        ]
      },
      {
        "long_name": "Santiago",
        "short_name": "Santiago",
        "types": [
          "administrative_area_level_2",
          "political"
        ]
      },
      {
        "long_name": "Región Metropolitana",
        "short_name": "Región Metropolitana",
        "types": [
          "administrative_area_level_1",
          "political"
        ]
      }
    ],
    "formatted_address": "Pudahuel, Región Metropolitana, Chile",
    "geometry": {
      "location": {
        "lat": -33.4440856,
        "lng": -70.75290199999999
      },
      "location_type": "GEOMETRIC_CENTER",
      "viewport": {
        "northeast": {
          "lat": -33.4427366197085,
          "lng": -70.75155301970848
        },
        "southwest": {
          "lat": -33.4454345802915,
          "lng": -70.75425098029149
        }
      }
    },
    "place_id": "ChIJM6dYe7fDYpYRJKADiHyA-90",
    "types": [
      "bus_station",
      "establishment",
      "point_of_interest",
      "transit_station"
    ]
  },
  "lat": -33.4440856,
  "lng": -70.75290199999999
}