{
  "fechaprediccion": "2017-07-31",
  "horaprediccion": "15:44",
  "nomett": "PARADA 3 / MATUCANA   AV. MAPOCHO",
  "paradero": "PJ287",
  "respuestaParadero": "",
  "servicios": {
    "item": [
      {
        "codigorespuesta": "00",
        "distanciabus1": "1112",
        "distanciabus2": "1672",
        "horaprediccionbus1": "Menos de 5 min.",
        "horaprediccionbus2": "Entre 04 Y 08 min. ",
        "ppubus1": "BJFC-36",
        "ppubus2": "BJFC-32",
        "respuestaServicio": "",
        "servicio": "502",
        "color": "#0093B3",
        "destino": "Cantagallo",
        "sentido": "1",
        "itinerario": false,
        "codigo": "U5"
      },
      {
        "codigorespuesta": "11",
        "distanciabus1": null,
        "distanciabus2": null,
        "horaprediccionbus1": null,
        "horaprediccionbus2": null,
        "ppubus1": null,
        "ppubus2": null,
        "respuestaServicio": "Fuera de horario de operacion para este paradero",
        "servicio": "502C",
        "color": "#0093B3",
        "destino": "Santiago",
        "sentido": "1",
        "itinerario": false,
        "codigo": "U5"
      },
      {
        "codigorespuesta": "00",
        "distanciabus1": "507",
        "distanciabus2": "547",
        "horaprediccionbus1": "Menos de 5 min.",
        "horaprediccionbus2": "Menos de 5 min.",
        "ppubus1": "BJFD-71",
        "ppubus2": "BJFB-81",
        "respuestaServicio": "",
        "servicio": "503",
        "color": "#0093B3",
        "destino": "Vital Apoquindo",
        "sentido": "1",
        "itinerario": false,
        "codigo": "U5"
      },
      {
        "codigorespuesta": "00",
        "distanciabus1": "1141",
        "distanciabus2": "3141",
        "horaprediccionbus1": "Menos de 5 min.",
        "horaprediccionbus2": "Entre 07 Y 11 min. ",
        "ppubus1": "BJFB-25",
        "ppubus2": "CJRW-65",
        "respuestaServicio": "",
        "servicio": "504",
        "color": "#0093B3",
        "destino": "Hosp. Dipreca",
        "sentido": "1",
        "itinerario": false,
        "codigo": "U5"
      },
      {
        "codigorespuesta": "00",
        "distanciabus1": "1881",
        "distanciabus2": "5661",
        "horaprediccionbus1": "Menos de 5 min.",
        "horaprediccionbus2": "Entre 12 Y 20 min. ",
        "ppubus1": "BJFC-18",
        "ppubus2": "CJRZ-91",
        "respuestaServicio": "",
        "servicio": "517",
        "color": "#0093B3",
        "destino": "Peñalolén",
        "sentido": "1",
        "itinerario": false,
        "codigo": "U5"
      },
      {
        "codigorespuesta": "00",
        "distanciabus1": "2441",
        "distanciabus2": "5141",
        "horaprediccionbus1": "Entre 05 Y 09 min. ",
        "horaprediccionbus2": "Entre 11 Y 19 min. ",
        "ppubus1": "BJFB-29",
        "ppubus2": "BJFZ-44",
        "respuestaServicio": "",
        "servicio": "518",
        "color": "#0093B3",
        "destino": "Bilbao",
        "sentido": "1",
        "itinerario": false,
        "codigo": "U5"
      },
      {
        "codigorespuesta": "11",
        "distanciabus1": null,
        "distanciabus2": null,
        "horaprediccionbus1": null,
        "horaprediccionbus2": null,
        "ppubus1": null,
        "ppubus2": null,
        "respuestaServicio": "Fuera de horario de operacion para este paradero",
        "servicio": "546E",
        "color": "#0093B3",
        "destino": "Vitacura",
        "sentido": "1",
        "itinerario": false,
        "codigo": "U5"
      }
    ]
  },
  "urlLinkPublicidad": null,
  "urlPublicidad": "http://mkt.smsbus.cl/img/Cat11.jpg",
  "x": "-",
  "y": "-",
  "valid": true,
  "googleMaps": {
    "address_components": [
      {
        "long_name": "Chile",
        "short_name": "CL",
        "types": [
          "country",
          "political"
        ]
      },
      {
        "long_name": "Quinta Normal",
        "short_name": "Quinta Normal",
        "types": [
          "locality",
          "political"
        ]
      },
      {
        "long_name": "Quinta Normal",
        "short_name": "Quinta Normal",
        "types": [
          "administrative_area_level_3",
          "political"
        ]
      },
      {
        "long_name": "Santiago",
        "short_name": "Santiago",
        "types": [
          "administrative_area_level_2",
          "political"
        ]
      },
      {
        "long_name": "Región Metropolitana",
        "short_name": "Región Metropolitana",
        "types": [
          "administrative_area_level_1",
          "political"
        ]
      }
    ],
    "formatted_address": "Quinta Normal, Región Metropolitana, Chile",
    "geometry": {
      "location": {
        "lat": -33.4330348,
        "lng": -70.681951
      },
      "location_type": "GEOMETRIC_CENTER",
      "viewport": {
        "northeast": {
          "lat": -33.43168581970851,
          "lng": -70.68060201970849
        },
        "southwest": {
          "lat": -33.4343837802915,
          "lng": -70.68329998029151
        }
      }
    },
    "place_id": "ChIJsXhQO0bEYpYRDXy85p6nO_k",
    "types": [
      "bus_station",
      "establishment",
      "point_of_interest",
      "transit_station"
    ]
  },
  "lat": -33.4330348,
  "lng": -70.681951
}