{
  "fechaprediccion": "2017-07-31",
  "horaprediccion": "15:42",
  "nomett": "MAR DE CHILE ESQ. / COSTANERA SUR",
  "paradero": "PJ709",
  "respuestaParadero": "",
  "servicios": {
    "item": [
      {
        "codigorespuesta": "00",
        "distanciabus1": "1133",
        "distanciabus2": "4783",
        "horaprediccionbus1": "Menos de 5 min.",
        "horaprediccionbus2": "Entre 11 Y 17 min. ",
        "ppubus1": "BJFC-63",
        "ppubus2": "BJFF-45",
        "respuestaServicio": "",
        "servicio": "J04",
        "color": "#0093B3",
        "destino": "La Alianza",
        "sentido": "1",
        "itinerario": false,
        "codigo": "U5"
      }
    ]
  },
  "urlLinkPublicidad": null,
  "urlPublicidad": "http://mkt.smsbus.cl/img/Cat11.jpg",
  "x": "-",
  "y": "-",
  "valid": true,
  "googleMaps": {
    "address_components": [
      {
        "long_name": "Chile",
        "short_name": "CL",
        "types": [
          "country",
          "political"
        ]
      },
      {
        "long_name": "Cerro Navia",
        "short_name": "Cerro Navia",
        "types": [
          "administrative_area_level_3",
          "political"
        ]
      },
      {
        "long_name": "Santiago",
        "short_name": "Santiago",
        "types": [
          "administrative_area_level_2",
          "political"
        ]
      },
      {
        "long_name": "Región Metropolitana",
        "short_name": "Región Metropolitana",
        "types": [
          "administrative_area_level_1",
          "political"
        ]
      }
    ],
    "formatted_address": "Cerro Navia, Región Metropolitana, Chile",
    "geometry": {
      "location": {
        "lat": -33.4147486,
        "lng": -70.7651198
      },
      "location_type": "GEOMETRIC_CENTER",
      "viewport": {
        "northeast": {
          "lat": -33.4133996197085,
          "lng": -70.76377081970848
        },
        "southwest": {
          "lat": -33.4160975802915,
          "lng": -70.7664687802915
        }
      }
    },
    "place_id": "ChIJBX8IDoLBYpYRV1TxTJKMmlY",
    "types": [
      "bus_station",
      "establishment",
      "point_of_interest",
      "transit_station"
    ]
  },
  "lat": -33.4147486,
  "lng": -70.7651198
}